{
  "title": "obra/superpowers",
  "url": "https://github.com/obra/superpowers",
  "source": "github",
  "date": "2026-05-15T09:51:32.024554+00:00",
  "content": "An agentic skills framework & software development methodology that works.",
  "language": "Shell",
  "popularity": "stars:192004",
  "summary": "Obra/Superpowers是一个实用的智能体技能框架与软件开发方法论，旨在提升开发效率与协作能力。",
  "tags": [
    "智能体",
    "技能框架",
    "软件开发方法论",
    "开发效率",
    "协作"
  ],
  "score": 0.8,
  "reason": "摘要清晰、技术深度合理、相关性好，但摘要略显简略，原创性评分适当降低。",
  "id": "article-20260515-002",
  "updated_at": "2026-05-15T09:52:08.029243+00:00"
}